{"NA1_4470141834": [false, "Volibear", "MasterYi", "Katarina", "Caitlyn", "Velkoz", "Swain", "Graves", "Zed", "Tristana", "Blitzcrank"], "NA1_4407409724": [true, "Kayle", "Amumu", "Velkoz", "Lucian", "Thresh", "Jax", "Ekko", "Viktor", "Jhin", "Renata"], "NA1_4248233127": [true, "Jax", "Nocturne", "Lux", "Sivir", "Galio", "Malphite", "RekSai", "Anivia", "Vayne", "Nami"], "NA1_4353509900": [true, "Nasus", "Nocturne", "Veigar", "Graves", "Yuumi", "Volibear", "Skarner", "Zoe", "Lucian", "Thresh"], "NA1_4474542439": [true, "Sion", "Trundle", "Fizz", "Ezreal", "Teemo", "Darius", "Shaco", "Malzahar", "Samira", "Amumu"], "NA1_4444625499": [true, "Kled", "Pantheon", "Zed", "Lucian", "FiddleSticks", "Volibear", "Belveth", "Yasuo", "Caitlyn", "Brand"], "NA1_4456673227": [false, "Kaisa", "Vi", "Lucian", "Seraphine", "Senna", "Urgot", "Belveth", "Ryze", "Caitlyn", "Lux"], "NA1_4418549369": [false, "Jax", "Hecarim", "Lux", "Draven", "Soraka", "Darius", "Ivern", "Nocturne", "Tristana", "Nami"], "NA1_4475882565": [true, "Sejuani", "Diana", "Gangplank", "Kaisa", "Pyke", "Mordekaiser", "Amumu", "Ekko", "Aphelios", "Morgana"], "NA1_4425455843": [true, "Irelia", "MasterYi", "Leblanc", "Ashe", "Poppy", "Morgana", "Khazix", "Ahri", "Jinx", "Pyke"], "NA1_4415700666": [false, "DrMundo", "Udyr", "Yone", "KogMaw", "Janna", "Renekton", "Rammus", "Katarina", "Ashe", "Zyra"], "NA1_4391541605": [false, "Shyvana", "Jax", "Zed", "Jinx", "Soraka", "Gangplank", "Hecarim", "Sion", "Jhin", "Ashe"], "NA1_4267999463": [true, "Jax", "Ekko", "Zed", "Jhin", "Lux", "Darius", "Volibear", "Yone", "Kaisa", "Seraphine"], "NA1_4470071400": [false, "Garen", "Shaco", "Akali", "Twitch", "Maokai", "Lillia", "Warwick", "Yasuo", "Jinx", "Janna"], "NA1_4472822962": [false, "Darius", "Shaco", "Kassadin", "Samira", "Seraphine", "Aatrox", "Rammus", "Syndra", "Yasuo", "Taric"], "NA1_4473966219": [false, "Aatrox", "Sejuani", "Sylas", "Jhin", "Janna", "Gangplank", "Maokai", "Zed", "Caitlyn", "Zilean"], "NA1_4463304176": [true, "Nasus", "Zac", "Chogath", "MissFortune", "Lulu", "Jax", "MasterYi", "Vladimir", "Jinx", "Thresh"], "NA1_4460616112": [true, "Riven", "Zac", "Yasuo", "Tristana", "Blitzcrank", "Teemo", "Ziggs", "Vi", "Sivir", "Sona"], "NA1_4470515082": [false, "Fizz", "Nilah", "Yasuo", "Jhin", "Pantheon", "Ornn", "JarvanIV", "Diana", "Ezreal", "Thresh"], "NA1_4378789567": [true, "Gangplank", "Trundle", "Qiyana", "Aphelios", "Zilean", "Yorick", "Ekko", "Swain", "Vayne", "Karma"], "NA1_4467732244": [false, "Orianna", "Amumu", "Akali", "Jinx", "Soraka", "Garen", "Graves", "Syndra", "Aphelios", "Vex"], "NA1_4464995195": [true, "Urgot", "Hecarim", "Azir", "Jinx", "Lulu", "Ornn", "Kindred", "Rumble", "Aphelios", "Nami"], "NA1_4354317778": [true, "Yorick", "Kayn", "Fizz", "Ezreal", "Rakan", "Riven", "MasterYi", "Diana", "Lucian", "Galio"], "NA1_4437852105": [true, "Garen", "Nunu", "TwistedFate", "MissFortune", "Sona", "Sion", "Sejuani", "Sett", "Sivir", "Neeko"], "NA1_4467820585": [true, "Aatrox", "Skarner", "Lux", "Draven", "Morgana", "Garen", "Hecarim", "Zilean", "Jinx", "Leona"], "NA1_4452159468": [true, "Sejuani", "Vi", "Lissandra", "Ezreal", "Nami", "Volibear", "Gragas", "Viktor", "Ashe", "Maokai"], "NA1_4465388948": [true, "Renekton", "Diana", "Sylas", "Jinx", "Brand", "Malphite", "Graves", "Anivia", "Twitch", "Swain"], "NA1_4458019481": [true, "Quinn", "Trundle", "Malzahar", "MissFortune", "Seraphine", "TahmKench", "Kayn", "Ryze", "Jhin", "Nami"], "NA1_4393894987": [false, "Jax", "Kayn", "Orianna", "MissFortune", "Nami", "Cassiopeia", "Evelynn", "Gangplank", "Kaisa", "Leona"], "NA1_4455491144": [false, "Tryndamere", "MasterYi", "Sett", "MissFortune", "Morgana", "Garen", "Chogath", "Ekko", "Kaisa", "Udyr"], "NA1_4371191986": [false, "Lillia", "Kindred", "Sett", "Jinx", "Yuumi", "Kayle", "Diana", "Annie", "MissFortune", "Thresh"], "NA1_4454920998": [true, "Sett", "Amumu", "Quinn", "Varus", "Lux", "TahmKench", "Elise", "Yone", "Yuumi", "Seraphine"], "NA1_4363112491": [true, "Mordekaiser", "Volibear", "Akali", "Samira", "Seraphine", "Kayle", "Zac", "Zed", "Caitlyn", "Blitzcrank"], "NA1_4429775711": [false, "Teemo", "Pantheon", "Kennen", "Twitch", "Karma", "Vladimir", "Evelynn", "Lux", "Kaisa", "Renata"], "NA1_4453879660": [true, "Camille", "Mordekaiser", "Akali", "MissFortune", "Lux", "Brand", "Graves", "Veigar", "Jinx", "Renata"], "NA1_4465664545": [true, "Gnar", "Maokai", "Akali", "Tristana", "Bard", "Darius", "Amumu", "Malzahar", "Kennen", "Lux"], "NA1_4472405711": [false, "Nocturne", "Rammus", "Sylas", "Kaisa", "Nami", "Renekton", "Amumu", "Zed", "Jinx", "Zyra"], "NA1_4445237299": [false, "Singed", "Graves", "Sylas", "Jhin", "Zyra", "Rengar", "Khazix", "Corki", "Ashe", "Nami"], "NA1_4465387770": [false, "Sett", "Graves", "Ahri", "Samira", "Bard", "Aatrox", "Evelynn", "Veigar", "MissFortune", "Sona"], "NA1_4422873341": [false, "Aatrox", "Zac", "Zed", "MissFortune", "Nami", "Teemo", "Udyr", "Swain", "Jhin", "Senna"], "NA1_4472977983": [true, "Mordekaiser", "Kayn", "Viktor", "Kaisa", "Shen", "Nasus", "Viego", "Zed", "Ashe", "Yuumi"], "NA1_4416618812": [false, "MonkeyKing", "MasterYi", "Ezreal", "Caitlyn", "Lux", "Mordekaiser", "Diana", "Anivia", "Twitch", "Senna"], "NA1_4428069068": [true, "Gangplank", "Nunu", "Yasuo", "Caitlyn", "Seraphine", "Jax", "Belveth", "Swain", "Lucian", "Pyke"], "NA1_4456887089": [false, "Maokai", "Rammus", "Sylas", "Kaisa", "Ashe", "Aatrox", "Ekko", "Yone", "MissFortune", "Soraka"], "NA1_4446843988": [false, "Yorick", "Graves", "Lux", "Jhin", "Lulu", "Gangplank", "MasterYi", "Viktor", "Varus", "Seraphine"], "NA1_4425356863": [true, "Riven", "Kindred", "Ahri", "Draven", "Lux", "Mordekaiser", "RekSai", "Sylas", "Lucian", "Leona"], "NA1_4450557582": [false, "Jax", "Sion", "Vladimir", "Kaisa", "Zyra", "Irelia", "Graves", "Corki", "MissFortune", "Sona"], "NA1_4443028762": [true, "Garen", "Belveth", "Zilean", "Jhin", "Xerath", "TahmKench", "FiddleSticks", "Brand", "Kaisa", "Janna"], "NA1_4465738179": [false, "Kayle", "Kayn", "Zed", "Aphelios", "Soraka", "Sett", "MasterYi", "Sylas", "Lucian", "Nami"], "NA1_4322606395": [true, "Illaoi", "Volibear", "Lux", "Vayne", "Pyke", "Urgot", "Shyvana", "Yone", "Lucian", "Brand"], "NA1_4430213751": [true, "Quinn", "Rengar", "Volibear", "Lucian", "Nami", "Mordekaiser", "Vi", "TwistedFate", "Aphelios", "Senna"], "NA1_4463692649": [true, "Shen", "Belveth", "Gragas", "Samira", "Lulu", "Akshan", "MasterYi", "Irelia", "Jhin", "Maokai"], "NA1_4473486327": [false, "Darius", "Udyr", "Azir", "Ashe", "Zyra", "Aatrox", "Amumu", "Annie", "Kaisa", "Karma"], "NA1_4465279533": [true, "Malphite", "FiddleSticks", "Leblanc", "Kalista", "Renata", "Fiora", "Trundle", "Draven", "Jhin", "Lux"], "NA1_4447982904": [true, "Trundle", "MasterYi", "Katarina", "Zeri", "Alistar", "Yorick", "Hecarim", "Viktor", "Ezreal", "Poppy"], "NA1_4460427692": [true, "Chogath", "Khazix", "Maokai", "Seraphine", "Senna", "Udyr", "Zac", "Akali", "MissFortune", "Thresh"], "NA1_4465911192": [true, "Rengar", "Nunu", "Zilean", "Jinx", "Ashe", "Renekton", "Udyr", "Syndra", "Jhin", "Leona"], "NA1_4365446204": [false, "Fiora", "Mordekaiser", "Katarina", "Twitch", "Swain", "Pantheon", "MasterYi", "Galio", "Jhin", "Karma"], "NA1_4469627703": [true, "Lillia", "Karthus", "Yone", "Ezreal", "Nautilus", "Kled", "Graves", "Yasuo", "Jinx", "Karma"], "NA1_4441084436": [true, "Yorick", "Vi", "Leblanc", "MissFortune", "Maokai", "Urgot", "Amumu", "Vladimir", "Sivir", "Rell"], "NA1_4457933661": [true, "Aatrox", "Evelynn", "Veigar", "Twitch", "Blitzcrank", "Urgot", "Diana", "Vi", "Vayne", "Trundle"], "NA1_4414407140": [true, "Illaoi", "Shaco", "Annie", "Ashe", "Thresh", "Ornn", "Rengar", "Velkoz", "Samira", "Alistar"], "NA1_4474358139": [true, "Teemo", "Ekko", "Zed", "KogMaw", "Yuumi", "Fiora", "Elise", "Akali", "Samira", "Nautilus"], "NA1_4464032755": [true, "Fiora", "Kindred", "Ekko", "Ashe", "Zyra", "Darius", "Sejuani", "Irelia", "Caitlyn", "Karma"], "NA1_4311410061": [false, "Nasus", "Karthus", "Teemo", "Lucian", "Renata", "Irelia", "Evelynn", "Katarina", "Senna", "Seraphine"], "NA1_4463657651": [false, "Vayne", "Rengar", "Brand", "Caitlyn", "Pyke", "Darius", "Kayn", "Fizz", "Samira", "Shen"], "NA1_4456334674": [false, "Illaoi", "Nasus", "Veigar", "Caitlyn", "Senna", "Yorick", "Kayn", "Brand", "Nilah", "Ashe"], "NA1_4450731731": [false, "Yorick", "Ekko", "Akshan", "Kaisa", "Lulu", "Shen", "MasterYi", "Sylas", "Ashe", "Soraka"], "NA1_4321148045": [true, "Yasuo", "Kayn", "Malphite", "Samira", "Swain", "Teemo", "MasterYi", "Annie", "Lucian", "Nami"], "NA1_4467324612": [false, "Vladimir", "Evelynn", "Akshan", "Xayah", "Rakan", "Mordekaiser", "Shaco", "Ahri", "Ezreal", "Senna"], "NA1_4416112732": [true, "Rumble", "Shyvana", "Jax", "Caitlyn", "Nautilus", "Tryndamere", "DrMundo", "Talon", "Nilah", "Zilean"], "NA1_4318948953": [false, "Jax", "Vi", "Chogath", "Lucian", "Senna", "MonkeyKing", "Zac", "Irelia", "Jhin", "Xerath"], "NA1_4101127799": [true, "Jax", "Graves", "Jayce", "Veigar", "Ashe", "Irelia", "Viego", "Heimerdinger", "Caitlyn", "Nami"], "NA1_4463228033": [true, "Renekton", "MasterYi", "Syndra", "Caitlyn", "Morgana", "Vladimir", "Rammus", "Leblanc", "MissFortune", "Pyke"], "NA1_4457958966": [true, "Mordekaiser", "Shyvana", "Akshan", "Kaisa", "Maokai", "Ornn", "Ekko", "Yone", "Kalista", "Alistar"], "NA1_4407019570": [false, "Kled", "Volibear", "Annie", "Varus", "Zyra", "Gwen", "DrMundo", "XinZhao", "MissFortune", "Xerath"], "NA1_4371043018": [true, "Veigar", "RekSai", "Kled", "Jhin", "Xerath", "Karma", "Lillia", "Zed", "Draven", "Rakan"], "NA1_4465069339": [false, "Sett", "JarvanIV", "Ahri", "Varus", "Morgana", "Maokai", "Udyr", "Syndra", "Tristana", "Lux"], "NA1_4462057225": [true, "Mordekaiser", "Warwick", "Gangplank", "Kaisa", "Pantheon", "Sett", "Vi", "Kassadin", "Xayah", "Soraka"], "NA1_4365537321": [false, "Sejuani", "Kaisa", "Irelia", "Jhin", "Nami", "Samira", "Hecarim", "Yasuo", "Seraphine", "Senna"], "NA1_4471662094": [true, "Gangplank", "Shyvana", "Veigar", "Ezreal", "Rell", "Singed", "Pantheon", "Sylas", "MissFortune", "Taric"], "NA1_4303462468": [false, "Garen", "Kindred", "Fizz", "Kaisa", "Brand", "Nasus", "Nocturne", "Galio", "Aphelios", "Morgana"], "NA1_4474441107": [false, "Urgot", "Amumu", "Ahri", "Samira", "Lux", "Fiora", "Graves", "Ziggs", "Tristana", "Blitzcrank"], "NA1_4382719176": [true, "Kayle", "Twitch", "Malphite", "Seraphine", "Renata", "Yone", "Kayn", "Irelia", "Jinx", "Pantheon"], "NA1_4470730114": [false, "Mordekaiser", "Karthus", "Zed", "Kalista", "Yuumi", "Shyvana", "Gwen", "Cassiopeia", "Caitlyn", "Sona"], "NA1_4464184400": [true, "Teemo", "Poppy", "Riven", "Xayah", "Thresh", "Yasuo", "Shyvana", "Azir", "MissFortune", "Leona"], "NA1_4445944489": [false, "Malzahar", "FiddleSticks", "Pantheon", "Zeri", "Senna", "Sett", "MasterYi", "Lux", "MissFortune", "Nautilus"], "NA1_4473381378": [true, "Nasus", "Graves", "Viktor", "Sivir", "Senna", "Malphite", "Nidalee", "Yasuo", "Draven", "Bard"], "NA1_4449560886": [true, "Sett", "Vi", "Syndra", "Ezreal", "Soraka", "Gnar", "Amumu", "Diana", "Zeri", "Yuumi"], "NA1_4450043478": [true, "Teemo", "Viego", "Yasuo", "MissFortune", "Ornn", "Aatrox", "JarvanIV", "Katarina", "Kaisa", "Nautilus"], "NA1_4420439744": [true, "Kayle", "Nocturne", "Zed", "KogMaw", "Zyra", "Illaoi", "Nunu", "Ahri", "Zeri", "Amumu"], "NA1_4452259862": [false, "Nasus", "MasterYi", "Taliyah", "Kalista", "Leona", "Fiora", "Rammus", "Malzahar", "MissFortune", "Brand"], "NA1_4470653870": [false, "Jax", "Diana", "Sylas", "Zeri", "Morgana", "Poppy", "Warwick", "Xerath", "Jhin", "Karma"], "NA1_4458778628": [false, "Udyr", "JarvanIV", "Brand", "Jhin", "Zyra", "Urgot", "Vi", "Sylas", "Ezreal", "TahmKench"], "NA1_4441845315": [true, "TahmKench", "Hecarim", "Gangplank", "Lucian", "Rell", "Mordekaiser", "Kayn", "Zed", "Vayne", "Alistar"], "NA1_4476402118": [true, "Irelia", "Amumu", "Heimerdinger", "Xayah", "Morgana", "Darius", "Warwick", "Lux", "Jhin", "Pyke"], "NA1_4239724549": [false, "Sion", "Volibear", "Kassadin", "Aphelios", "Karma", "Nasus", "Viego", "Akali", "Samira", "Thresh"], "NA1_4461027095": [false, "Singed", "Graves", "Viktor", "Draven", "Thresh", "Malphite", "Warwick", "Syndra", "Jhin", "Senna"], "NA1_4470576431": [true, "Tryndamere", "Diana", "Orianna", "Tristana", "Pantheon", "Darius", "Maokai", "Lissandra", "Aphelios", "Thresh"], "NA1_4309573874": [false, "Renekton", "Nidalee", "Viego", "Vayne", "Nautilus", "MonkeyKing", "Olaf", "Talon", "Ezreal", "Xerath"], "NA1_4453027200": [true, "Vayne", "Evelynn", "Mordekaiser", "Jhin", "Seraphine", "Gnar", "FiddleSticks", "Sylas", "Ezreal", "Lux"], "NA1_4475554745": [false, "Irelia", "Blitzcrank", "Annie", "Kaisa", "Janna", "Quinn", "MasterYi", "LeeSin", "Jhin", "Thresh"], "NA1_4394140200": [false, "Darius", "Kayn", "Galio", "Kaisa", "Velkoz", "Vayne", "Olaf", "Yone", "Ezreal", "Brand"], "NA1_4474158924": [false, "Gangplank", "Udyr", "Talon", "Nilah", "Lux", "Quinn", "Gragas", "Viktor", "Tristana", "Morgana"], "NA1_4454210204": [false, "Nasus", "Udyr", "Kennen", "MissFortune", "Leona", "Maokai", "LeeSin", "Ahri", "Varus", "Janna"], "NA1_4103612339": [true, "Camille", "Olaf", "Syndra", "Jhin", "Maokai", "Riven", "Hecarim", "Viktor", "Aphelios", "Lulu"], "NA1_4433121412": [false, "Darius", "Belveth", "Katarina", "Draven", "Pantheon", "Yorick", "LeeSin", "Viktor", "Jhin", "Lux"], "NA1_4421030147": [true, "Akali", "Zac", "Zed", "Jhin", "Lulu", "Gangplank", "Morgana", "Urgot", "Ezreal", "Janna"], "NA1_4473667686": [false, "Nasus", "Karthus", "Akshan", "Swain", "Nami", "Maokai", "Diana", "Viktor", "Jinx", "Senna"], "NA1_4448183268": [true, "Kennen", "Evelynn", "Yone", "Jhin", "Nautilus", "Swain", "Vi", "Irelia", "MissFortune", "Lux"], "NA1_4475599617": [true, "Urgot", "Diana", "Vladimir", "Jinx", "Leona", "Aatrox", "Gragas", "Sylas", "Veigar", "Twitch"], "NA1_4194065427": [false, "Volibear", "Trundle", "Malzahar", "Draven", "Nami", "Chogath", "Warwick", "Ziggs", "Xayah", "Yuumi"], "NA1_4437722759": [false, "Shen", "Urgot", "Yasuo", "Ezreal", "Nami", "Volibear", "Ekko", "Akshan", "Tristana", "Nasus"], "NA1_4475593807": [false, "Heimerdinger", "Rengar", "Lucian", "Ashe", "Renata", "Chogath", "Shaco", "Anivia", "Sivir", "Senna"], "NA1_4449493113": [false, "Gangplank", "Hecarim", "Ahri", "Kaisa", "Leona", "Aatrox", "Volibear", "TwistedFate", "Lucian", "Zilean"], "NA1_4451349465": [false, "Yorick", "Elise", "Anivia", "Caitlyn", "Senna", "Warwick", "Belveth", "Vladimir", "Xayah", "Sona"], "NA1_4467448894": [false, "Aatrox", "Viego", "Pantheon", "Samira", "Senna", "Shen", "Udyr", "Swain", "Jhin", "Morgana"], "NA1_4427650963": [true, "Aatrox", "Khazix", "Seraphine", "MissFortune", "Zyra", "Riven", "Karthus", "Qiyana", "Lucian", "Nami"], "NA1_4383865510": [false, "Chogath", "Viego", "Akali", "Seraphine", "Senna", "Urgot", "Nautilus", "Malphite", "Yasuo", "Taric"], "NA1_4470658920": [true, "Nasus", "Evelynn", "Talon", "Seraphine", "Senna", "Sejuani", "JarvanIV", "Akali", "Tristana", "Lulu"], "NA1_4467551659": [false, "Kled", "JarvanIV", "Yone", "MissFortune", "Lux", "DrMundo", "FiddleSticks", "Yasuo", "Caitlyn", "Senna"], "NA1_4467125324": [true, "Renekton", "Mordekaiser", "Viktor", "Ezreal", "Ashe", "Fiora", "Viego", "Seraphine", "MissFortune", "Nami"], "NA1_4457068592": [true, "Tryndamere", "Rengar", "Annie", "Varus", "Thresh", "TahmKench", "Kayn", "Syndra", "Tristana", "Lulu"], "NA1_4428518344": [false, "Aatrox", "Ekko", "Katarina", "Ezreal", "Morgana", "Viego", "FiddleSticks", "Ahri", "Kaisa", "Lulu"], "NA1_4403787900": [false, "Urgot", "Nunu", "Yone", "Yasuo", "Alistar", "Ornn", "Nocturne", "Sylas", "Kalista", "Sona"], "NA1_4396366697": [true, "Irelia", "Viego", "Neeko", "Sivir", "Blitzcrank", "Heimerdinger", "Kayn", "Vladimir", "Kaisa", "Ashe"], "NA1_4474024351": [false, "Chogath", "Nidalee", "Ziggs", "Kaisa", "Senna", "DrMundo", "Vi", "Xerath", "Ashe", "Karma"], "NA1_4474398629": [true, "Irelia", "FiddleSticks", "Ziggs", "Caitlyn", "Nautilus", "Urgot", "Warwick", "Fizz", "MissFortune", "Pyke"], "NA1_4468435655": [false, "Kayle", "Vi", "Sylas", "Samira", "Swain", "Aatrox", "Zed", "Syndra", "Ezreal", "Leblanc"], "NA1_4423450418": [false, "Shaco", "Qiyana", "Chogath", "MissFortune", "FiddleSticks", "Udyr", "MasterYi", "Lux", "Tristana", "Nami"], "NA1_4470388385": [true, "Kennen", "Viego", "Lux", "Sivir", "Maokai", "Poppy", "FiddleSticks", "Yasuo", "Vayne", "Lulu"], "NA1_4408442981": [false, "Tryndamere", "Shyvana", "Sylas", "Ashe", "Soraka", "Mordekaiser", "Amumu", "Zed", "Caitlyn", "Nautilus"], "NA1_4457479505": [false, "Renekton", "Graves", "Viktor", "Jhin", "Seraphine", "Chogath", "JarvanIV", "Ryze", "Caitlyn", "Soraka"], "NA1_4461411494": [true, "Aatrox", "Hecarim", "Sylas", "Jinx", "Zilean", "Malphite", "Khazix", "Syndra", "Lucian", "Leona"], "NA1_4437199614": [false, "Darius", "Sejuani", "Xerath", "Jinx", "Sona", "Garen", "Amumu", "Gangplank", "Tristana", "Swain"], "NA1_4391424438": [true, "Kayle", "Zac", "Yone", "Ezreal", "Xerath", "Nasus", "MasterYi", "Sylas", "Sivir", "Pyke"], "NA1_4451276710": [false, "Aatrox", "Hecarim", "Cassiopeia", "Xayah", "Sona", "Sett", "Diana", "Fizz", "Kaisa", "Morgana"], "NA1_4431485560": [false, "Nasus", "Hecarim", "Yasuo", "Ahri", "Brand", "Darius", "Viego", "Cassiopeia", "Caitlyn", "Seraphine"], "NA1_4307409686": [false, "Swain", "Kindred", "Sylas", "Kaisa", "Senna", "Singed", "Hecarim", "TwistedFate", "Lucian", "Yuumi"], "NA1_4276349050": [true, "Darius", "Nunu", "Annie", "Kaisa", "Zilean", "Urgot", "Rammus", "Yasuo", "Jinx", "Zyra"], "NA1_4473497466": [false, "Udyr", "Trundle", "Yasuo", "Kaisa", "Volibear", "DrMundo", "MasterYi", "Sett", "Jhin", "Yuumi"], "NA1_4465310088": [true, "Shen", "Udyr", "Sylas", "Aphelios", "Janna", "Sion", "Sejuani", "Pantheon", "Ezreal", "Lux"], "NA1_4462370314": [false, "Udyr", "Diana", "Galio", "Tristana", "Pyke", "Yorick", "Nocturne", "Sylas", "MissFortune", "Renata"], "NA1_4473642759": [false, "Volibear", "Vi", "Sylas", "Kaisa", "Thresh", "Graves", "Khazix", "Viktor", "Lucian", "Nami"], "NA1_4461273364": [true, "Renekton", "LeeSin", "Yone", "Caitlyn", "Lux", "Sett", "Kayn", "Varus", "Aphelios", "Bard"], "NA1_4391557809": [false, "Camille", "Elise", "Leblanc", "Draven", "Pyke", "Pantheon", "Belveth", "Yone", "Jhin", "Janna"], "NA1_4476318579": [false, "Sejuani", "Ekko", "Ahri", "Jhin", "Rakan", "Urgot", "Warwick", "Akali", "Caitlyn", "Rell"], "NA1_4470791020": [true, "Darius", "FiddleSticks", "Sylas", "Lucian", "Bard", "Ryze", "Viego", "Ahri", "Samira", "Nautilus"], "NA1_4473726712": [true, "Ornn", "Lillia", "Irelia", "Tristana", "Brand", "Jax", "Talon", "Syndra", "Draven", "Renata"], "NA1_4440255570": [false, "Riven", "Hecarim", "Garen", "Samira", "Alistar", "Yorick", "Belveth", "Fizz", "MissFortune", "Neeko"], "NA1_4458860915": [false, "Fiora", "Viego", "Fizz", "Draven", "Blitzcrank", "Yone", "Kindred", "Chogath", "Ezreal", "Swain"], "NA1_4439492958": [false, "Malphite", "Graves", "Talon", "Irelia", "LeeSin", "Maokai", "Hecarim", "Fizz", "Jhin", "Lulu"], "NA1_4463410610": [true, "Kled", "Diana", "Annie", "Ashe", "Shen", "Mordekaiser", "Belveth", "Ahri", "Twitch", "Thresh"], "NA1_4353326899": [false, "Volibear", "Pantheon", "Syndra", "Zeri", "Lulu", "Fiora", "Rengar", "Swain", "Ezreal", "Amumu"], "NA1_4464427507": [false, "Trundle", "Udyr", "Kassadin", "Tristana", "Ashe", "Sett", "LeeSin", "Zed", "Caitlyn", "MissFortune"], "NA1_4451049302": [false, "Jax", "Nidalee", "KogMaw", "Kaisa", "Thresh", "Ornn", "Kayn", "Viktor", "Ezreal", "Zyra"], "NA1_4283383672": [true, "Gwen", "Talon", "Yasuo", "Caitlyn", "Yuumi", "Chogath", "Amumu", "Syndra", "Kayle", "Sona"], "NA1_4474493193": [false, "Illaoi", "JarvanIV", "Brand", "Sivir", "Soraka", "Yorick", "Poppy", "Sylas", "Ezreal", "Thresh"], "NA1_4265983054": [true, "Irelia", "Volibear", "Malzahar", "Jhin", "Bard", "Fiora", "Ekko", "Yasuo", "MissFortune", "Nami"], "NA1_4471258361": [true, "Camille", "Kayn", "Malzahar", "Senna", "Velkoz", "Darius", "Nunu", "Syndra", "MissFortune", "Thresh"], "NA1_4387382995": [false, "Garen", "Udyr", "Akali", "Tristana", "Malphite", "Trundle", "Zac", "Vex", "Senna", "Velkoz"], "NA1_4473003231": [true, "Aatrox", "Rammus", "Yasuo", "Caitlyn", "Velkoz", "Karma", "Sejuani", "Riven", "Ashe", "Morgana"], "NA1_4460797487": [false, "Aatrox", "Graves", "Neeko", "Jhin", "Zyra", "Rammus", "Chogath", "Yasuo", "Caitlyn", "Ivern"], "NA1_4474385139": [true, "Yone", "Blitzcrank", "Anivia", "Vayne", "Senna", "Aatrox", "Kayn", "Vex", "Kaisa", "Soraka"], "NA1_4321894205": [true, "Aatrox", "JarvanIV", "Katarina", "Ziggs", "Zilean", "Trundle", "Kayn", "Qiyana", "Samira", "Kayle"], "NA1_4450096127": [false, "Yorick", "MonkeyKing", "Galio", "Ezreal", "Senna", "Gangplank", "Khazix", "Velkoz", "Kaisa", "Lux"], "NA1_4424254178": [false, "TahmKench", "Nidalee", "Yasuo", "MissFortune", "Velkoz", "Camille", "Trundle", "Malzahar", "Ashe", "Lulu"], "NA1_4428093071": [true, "Sion", "Trundle", "Akali", "Caitlyn", "Lux", "Gangplank", "Mordekaiser", "Katarina", "Vayne", "Lulu"], "NA1_4446987331": [false, "Gragas", "Shaco", "TwistedFate", "Brand", "Jhin", "Darius", "Nocturne", "Tristana", "Sivir", "Zilean"], "NA1_4466126293": [true, "Camille", "Morgana", "Sylas", "MissFortune", "Brand", "Kayle", "Sion", "Xerath", "Ezreal", "FiddleSticks"], "NA1_4352235129": [true, "Garen", "Khazix", "Swain", "Twitch", "Ashe", "Lillia", "Kayn", "Leblanc", "Veigar", "Sona"], "NA1_4446120631": [false, "Senna", "Shaco", "Velkoz", "Caitlyn", "Rell", "Talon", "Udyr", "Twitch", "Varus", "Thresh"], "NA1_4464154816": [false, "Gwen", "Hecarim", "Sylas", "Kaisa", "Nami", "Jax", "Lillia", "Yone", "MissFortune", "Blitzcrank"], "NA1_4466210049": [true, "Nasus", "Mordekaiser", "Ekko", "Caitlyn", "Lux", "Heimerdinger", "Amumu", "Zed", "Zilean", "Ezreal"], "NA1_4453074805": [true, "Gnar", "Ekko", "Karthus", "Twitch", "Ornn", "Teemo", "Rammus", "Vex", "Tristana", "FiddleSticks"], "NA1_4428446537": [true, "Mordekaiser", "Trundle", "Heimerdinger", "Jhin", "Senna", "Veigar", "Viego", "Katarina", "Yasuo", "Pyke"], "NA1_4464766605": [false, "Vayne", "Kayn", "Talon", "Ezreal", "Brand", "Darius", "Udyr", "Syndra", "Kaisa", "Ashe"], "NA1_4434877856": [false, "Sett", "Poppy", "Malzahar", "MissFortune", "Leona", "Udyr", "Volibear", "Diana", "Draven", "Lux"], "NA1_4455092944": [true, "Aatrox", "Karthus", "Qiyana", "Nilah", "Taric", "Sett", "Nunu", "Akali", "Caitlyn", "Morgana"], "NA1_4313113318": [true, "Garen", "Khazix", "Vladimir", "Ezreal", "Pantheon", "Teemo", "Udyr", "Akali", "Jhin", "Senna"], "NA1_4438535292": [false, "Camille", "Warwick", "Akshan", "Draven", "Rell", "Renekton", "Lillia", "Heimerdinger", "MissFortune", "Pantheon"], "NA1_4364565673": [true, "Ornn", "MonkeyKing", "Ahri", "Draven", "Senna", "Camille", "Kayn", "Vladimir", "Ashe", "Velkoz"], "NA1_4458106631": [false, "Nasus", "Taliyah", "Talon", "Jhin", "Zilean", "Yorick", "Volibear", "Galio", "Jinx", "Pyke"], "NA1_4463612905": [true, "Maokai", "Kayn", "Lux", "Kaisa", "Amumu", "Nasus", "Graves", "Singed", "Tristana", "Nautilus"], "NA1_4412240264": [true, "Yorick", "Trundle", "Syndra", "Ashe", "Soraka", "Mordekaiser", "FiddleSticks", "Pantheon", "Draven", "Thresh"], "NA1_4396310235": [true, "Gwen", "DrMundo", "Swain", "Kaisa", "Alistar", "Aatrox", "Trundle", "Akali", "MissFortune", "Leona"], "NA1_4440897935": [true, "Ornn", "LeeSin", "Nasus", "Kaisa", "Lux", "Lillia", "Kayn", "Yone", "Brand", "Lulu"], "NA1_4459393873": [false, "Jax", "Graves", "Vladimir", "Tristana", "Poppy", "Camille", "Diana", "Heimerdinger", "MissFortune", "Pyke"], "NA1_4275211781": [false, "Vayne", "Taliyah", "Veigar", "Sivir", "Senna", "Darius", "Graves", "Ahri", "Twitch", "Zyra"], "NA1_4469427415": [true, "Illaoi", "Hecarim", "Viktor", "Ashe", "Leona", "Udyr", "Sejuani", "Teemo", "Jhin", "Morgana"], "NA1_4277093430": [false, "Darius", "Kindred", "AurelionSol", "MissFortune", "Nautilus", "Teemo", "Nunu", "Xerath", "Tristana", "Pyke"]}